LICENSE
MANIFEST.in
setup.py
taiga_contrib_hall/__init__.py
taiga_contrib_hall/api.py
taiga_contrib_hall/apps.py
taiga_contrib_hall/compat.py
taiga_contrib_hall/models.py
taiga_contrib_hall/permissions.py
taiga_contrib_hall/serializers.py
taiga_contrib_hall/signal_handlers.py
taiga_contrib_hall/tasks.py
taiga_contrib_hall.egg-info/PKG-INFO
taiga_contrib_hall.egg-info/SOURCES.txt
taiga_contrib_hall.egg-info/dependency_links.txt
taiga_contrib_hall.egg-info/requires.txt
taiga_contrib_hall.egg-info/top_level.txt
taiga_contrib_hall/migrations/0001_initial.py
taiga_contrib_hall/migrations/__init__.py
taiga_contrib_hall/templates/taiga_contrib_hall/change.jinja
taiga_contrib_hall/templates/taiga_contrib_hall/create.jinja
taiga_contrib_hall/templates/taiga_contrib_hall/delete.jinja
taiga_contrib_hall/templates/taiga_contrib_hall/field-diff.jinja