Metadata-Version: 1.1
Name: taiga-contrib-hall
Version: 0.0.4
Summary: The Taiga plugin for hall integration
Home-page: https://github.com/taigaio/taiga-contrib-hall
Author: Jesús Espino García
Author-email: jesus.espino@kaleidos.net
License: AGPL
Keywords: taiga,hall,integration
Platform: UNKNOWN
Classifier: Programming Language :: Python
Classifier: Development Status :: 4 - Beta
Classifier: Framework :: Django
Classifier: Intended Audience :: Developers
Classifier: License :: OSI Approved :: GNU Affero General Public License v3
Classifier: Operating System :: OS Independent
Classifier: Programming Language :: Python
Classifier: Topic :: Internet :: WWW/HTTP
